LICENSE
README.md
setup.py
mktstructure/__init__.py
mktstructure/cmd_classify.py
mktstructure/cmd_clean.py
mktstructure/cmd_compute.py
mktstructure/cmd_download.py
mktstructure/cmd_download_mktdepth.py
mktstructure/main.py
mktstructure/request_templates.py
mktstructure/trth.py
mktstructure/trth_parser.c
mktstructure/utils.py
mktstructure.egg-info/PKG-INFO
mktstructure.egg-info/SOURCES.txt
mktstructure.egg-info/dependency_links.txt
mktstructure.egg-info/entry_points.txt
mktstructure.egg-info/requires.txt
mktstructure.egg-info/top_level.txt
mktstructure/measures/__init__.py
mktstructure/measures/ask_slope.py
mktstructure/measures/bid_slope.py
mktstructure/measures/bidask_spread.py
mktstructure/measures/effective_spread.py
mktstructure/measures/exceptions.py
mktstructure/measures/price_impact.py
mktstructure/measures/realized_spread.py
mktstructure/measures/scaled_depth_difference.py
mktstructure/measures/variance_ratio.py