Metadata-Version: 2.1
Name: mktstructure
Version: 0.2.9
Summary: Download data from Refinitiv Tick History and compute some market microstructure measures.
Home-page: https://github.com/mgao6767/mktstructure
Author: Mingze Gao
Author-email: mingze.gao@sydney.edu.au
License: MIT
Platform: UNKNOWN
Classifier: License :: OSI Approved :: MIT License
Classifier: Programming Language :: Python :: 3
Classifier: Programming Language :: Python :: 3.8
Classifier: Intended Audience :: End Users/Desktop
Classifier: Intended Audience :: Financial and Insurance Industry
Classifier: Intended Audience :: Education
Classifier: Intended Audience :: Science/Research
Classifier: Topic :: Scientific/Engineering :: Information Analysis
